aristotle_bg_workers/__init__.py
aristotle_bg_workers/apps.py
aristotle_bg_workers/celery.py
aristotle_bg_workers/helpers.py
aristotle_bg_workers/messages.py
aristotle_bg_workers/models.py
aristotle_bg_workers/signals.py
aristotle_bg_workers/tasks.py
aristotle_bg_workers/tests.py
aristotle_bg_workers/urls.py
aristotle_bg_workers/utils.py
aristotle_bg_workers/views.py
aristotle_bg_workers/migrations/0001_squashed_0002_extrataskinfo_date_started.py
aristotle_bg_workers/migrations/0002_extrataskinfo_celery_task_id.py
aristotle_bg_workers/migrations/__init__.py
aristotle_bg_workers/templates/aristotle_bg_workers/paginated_task_list.html
aristotle_bg_workers/templates/aristotle_bg_workers/task_history.html
aristotle_bg_workers/templates/aristotle_bg_workers/task_list.html
aristotle_bg_workers/templates/aristotle_bg_workers/task_runner.html
aristotle_dse/__init__.py
aristotle_dse/admin.py
aristotle_dse/apps.py
aristotle_dse/downloader.py
aristotle_dse/forms.py
aristotle_dse/models.py
aristotle_dse/urls.py
aristotle_dse/views.py
aristotle_dse/aristotle_help_files/concept_help/datacatalog.yaml
aristotle_dse/aristotle_help_files/concept_help/dataset.yaml
aristotle_dse/aristotle_help_files/concept_help/datasetspecification.yaml
aristotle_dse/aristotle_help_files/concept_help/distribution.yaml
aristotle_dse/management/__init__.py
aristotle_dse/management/commands/__init__.py
aristotle_dse/management/commands/load_ckan.py
aristotle_dse/migrations/0001_squashed_0013_now_with_dcat.py
aristotle_dse/migrations/0014_auto_20161023_2304.py
aristotle_dse/migrations/0015_auto_20170608_0044.py
aristotle_dse/migrations/0016_auto_20171111_2335.py
aristotle_dse/migrations/0017_auto_20180510_0615.py
aristotle_dse/migrations/0018_auto_20181107_0433.py
aristotle_dse/migrations/0019_auto_20190204_2106.py
aristotle_dse/migrations/0020_auto_20190206_1930.py
aristotle_dse/migrations/0021_auto_20190415_0012.py
aristotle_dse/migrations/0022_auto_20190501_1043.py
aristotle_metadata_registry-3.0.17.dist-info/LICENSE
aristotle_metadata_registry-3.0.17.dist-info/METADATA
aristotle_metadata_registry-3.0.17.dist-info/WHEEL
aristotle_metadata_registry-3.0.17.dist-info/entry_points.txt
aristotle_metadata_registry-3.0.17.dist-info/top_level.txt
aristotle_metadata_registry-3.0.17.dist-info/RECORD
