Metadata-Version: 2.1
Name: aristotle-metadata-registry
Version: 3.0.17
Summary: Aristotle-MDR is an open-source metadata registry as laid out by the requirements of the IEC/ISO 11179:2013 specification.
Home-page: https://github.com/aristotle-mdr/aristotle-metadata-registry
Author: Samuel Spencer
Author-email: sam@aristotlemetadata.com
License: Aristotle-MDR Modified BSD Licence
Platform: UNKNOWN
Classifier: Development Status :: 5 - Production/Stable
Classifier: Environment :: Web Environment
Classifier: Framework :: Django
Classifier: Intended Audience :: Healthcare Industry
Classifier: Intended Audience :: Information Technology
Classifier: Intended Audience :: Science/Research
Classifier: Intended Audience :: Developers
Classifier: Operating System :: OS Independent
Classifier: Programming Language :: Python
Classifier: Programming Language :: Python :: 3
Classifier: Programming Language :: Python :: 3.4
Classifier: Programming Language :: Python :: 3.5
Classifier: Programming Language :: Python :: 3.6
Classifier: Topic :: Internet :: WWW/HTTP
Classifier: Topic :: Internet :: WWW/HTTP :: Dynamic Content
Requires-Dist: requests
Requires-Dist: celery
Requires-Dist: django-celery-results (==1.0.4)
Requires-Dist: graphene-django (~=2.5.0)
Requires-Dist: graphene (~=2.1.7)
Requires-Dist: django-filter (~=2.2.0)
Requires-Dist: lxml
Requires-Dist: djangorestframework (>=3.8)
Requires-Dist: drf-yasg
Requires-Dist: django-filter
Requires-Dist: django-jsonforms
Requires-Dist: coreapi
Requires-Dist: Django (~=2.2.0)
Requires-Dist: six
Requires-Dist: pytz
Requires-Dist: pyyaml
Requires-Dist: dj-database-url
Requires-Dist: django-model-utils (>=2.3.1)
Requires-Dist: django-notifications-hq (==1.4)
Requires-Dist: django-braces
Requires-Dist: docutils
Requires-Dist: django-haystack (~=2.8.0)
Requires-Dist: django-ckeditor (>=5.3.0)
Requires-Dist: pillow
Requires-Dist: django-reversion (<2.1,>=2.0)
Requires-Dist: django-reversion-compare (~=0.8.0)
Requires-Dist: diff-match-patch
Requires-Dist: django-autocomplete-light (>=3.4.0)
Requires-Dist: django-bootstrap3 (<9.0,>8.0)
Requires-Dist: django-bootstrap3-datetimepicker-2 (>=2.5.0)
Requires-Dist: django-formtools (>=2.0)
Requires-Dist: django-autoslug
Requires-Dist: sqlparse
Requires-Dist: django-organizations
Requires-Dist: django-improved-user (>=1.0.0)
Requires-Dist: django-constrainedfilefield
Requires-Dist: python-magic (>=0.4.2jsonfield)
Requires-Dist: django-user-sessions
Requires-Dist: geoip2
Requires-Dist: django-webpack-loader
Requires-Dist: attrs
Requires-Dist: jsonschema
Requires-Dist: django-storages
Requires-Dist: bleach
Requires-Dist: pypandoc
Requires-Dist: weasyprint
Requires-Dist: pdfkit
Requires-Dist: PyPDF2
Requires-Dist: django-bulk-update
Requires-Dist: django-mptt
Requires-Dist: python-dateutil
